zoom_meet_attendance_helper/__init__.py
zoom_meet_attendance_helper/main.py
zoom_meet_attendance_visualizer-1.0.5.dist-info/LICENSE
zoom_meet_attendance_visualizer-1.0.5.dist-info/METADATA
zoom_meet_attendance_visualizer-1.0.5.dist-info/WHEEL
zoom_meet_attendance_visualizer-1.0.5.dist-info/top_level.txt
zoom_meet_attendance_visualizer-1.0.5.dist-info/RECORD
