Metadata-Version: 2.1
Name: zoom-meet-attendance-visualizer
Version: 1.0.5
Summary: Manage and visualize data collected using extension zoom_meet_attendance
Home-page: https://github.com/mahbd/zoom_meet_attendance_visualizer
Author: Mahmudul Alam
Author-email: mahmudula2000@gmail.com
License: UNKNOWN
Platform: UNKNOWN
Requires-Dist: matplotlib
Requires-Dist: seaborn
Requires-Dist: numpy (==1.19.3)
